{
  "name": "apollo-blockchain",
  "description": "Apollo blockchain backend",
  "version": "1.44.0",
  "dependencies": [
    {
      "name": "OpenJDK",
      "optional": false,
      "version_min": "11.0.6",
      "version_max": "13.0.2"
    },
    {
      "name": "apollo-blockchain-ext-deps",
      "optional": false,
      "version_min": "1.0.0",
      "version_max": "1.0.0"
    },
    {
      "name": "Apollo-web-ui",
      "optional": true,
      "version_min": "2.7.5",
      "version_max": "2.7.6"
    }
  ]
}